rsArtdToSimple/__init__.py
rsArtdToSimple/reformat.py
rsArtdToSimple-1.0.0.dist-info/LICENCE
rsArtdToSimple-1.0.0.dist-info/METADATA
rsArtdToSimple-1.0.0.dist-info/WHEEL
rsArtdToSimple-1.0.0.dist-info/entry_points.txt
rsArtdToSimple-1.0.0.dist-info/top_level.txt
rsArtdToSimple-1.0.0.dist-info/RECORD
